{
    "build": {
        "development": {
            "developmentClient": true,
            "distribution": "internal",
            "env": {
                "ANDROID_HOME": "/Users/racit/Library/Android/sdk"
            }
        },
        "preview": {
            "android": {
                "buildType": "apk"
            },
            "env": {
                "ANDROID_HOME": "/Users/racit/Library/Android/sdk"

            }
        },
        "production": {
            "env": {
                "ANDROID_HOME": "/Users/racit/Library/Android/sdk"
            }
        }
    }
}